{
    "name": "3",
    "frames": [
        {
            "timestamp": 10000,
            "objects": [
                {
                    "category": "obstacle",
                    "id": 0,
                    "attributes": {
                        "occluded": false,
                        "truncated": false,
                        "trafficLightColor": "none"
                    },
                    "box2d": {
                        "x1": 380.0,
                        "y1": 153.0,
                        "x2": 640.0,
                        "y2": 480.0
                    }
                },
                {
                    "category": "obstacle",
                    "id": 1,
                    "attributes": {
                        "occluded": false,
                        "truncated": false,
                        "trafficLightColor": "none"
                    },
                    "box2d": {
                        "x1": 0.0,
                        "y1": 104.0,
                        "x2": 254.0,
                        "y2": 440.0
                    }
                },
                {
                    "category": "area/drivable",
                    "id": 7,
                    "attributes": {},
                    "poly2d": [
                        [
                            253.0,
                            338.0,
                            "L"
                        ],
                        [
                            253.0,
                            341.0,
                            "L"
                        ],
                        [
                            252.0,
                            342.0,
                            "L"
                        ],
                        [
                            252.0,
                            346.0,
                            "L"
                        ],
                        [
                            251.0,
                            347.0,
                            "L"
                        ],
                        [
                            251.0,
                            348.0,
                            "L"
                        ],
                        [
                            250.0,
                            349.0,
                            "L"
                        ],
                        [
                            250.0,
                            350.0,
                            "L"
                        ],
                        [
                            245.0,
                            355.0,
                            "L"
                        ],
                        [
                            244.0,
                            355.0,
                            "L"
                        ],
                        [
                            243.0,
                            356.0,
                            "L"
                        ],
                        [
                            242.0,
                            356.0,
                            "L"
                        ],
                        [
                            241.0,
                            357.0,
                            "L"
                        ],
                        [
                            238.0,
                            357.0,
                            "L"
                        ],
                        [
                            237.0,
                            358.0,
                            "L"
                        ],
                        [
                            216.0,
                            358.0,
                            "L"
                        ],
                        [
                            212.0,
                            354.0,
                            "L"
                        ],
                        [
                            212.0,
                            353.0,
                            "L"
                        ],
                        [
                            211.0,
                            352.0,
                            "L"
                        ],
                        [
                            211.0,
                            351.0,
                            "L"
                        ],
                        [
                            210.0,
                            350.0,
                            "L"
                        ],
                        [
                            210.0,
                            349.0,
                            "L"
                        ],
                        [
                            209.0,
                            348.0,
                            "L"
                        ],
                        [
                            208.0,
                            349.0,
                            "L"
                        ],
                        [
                            202.0,
                            349.0,
                            "L"
                        ],
                        [
                            202.0,
                            353.0,
                            "L"
                        ],
                        [
                            203.0,
                            354.0,
                            "L"
                        ],
                        [
                            203.0,
                            365.0,
                            "L"
                        ],
                        [
                            204.0,
                            366.0,
                            "L"
                        ],
                        [
                            204.0,
                            388.0,
                            "L"
                        ],
                        [
                            203.0,
                            389.0,
                            "L"
                        ],
                        [
                            203.0,
                            400.0,
                            "L"
                        ],
                        [
                            202.0,
                            401.0,
                            "L"
                        ],
                        [
                            202.0,
                            406.0,
                            "L"
                        ],
                        [
                            201.0,
                            407.0,
                            "L"
                        ],
                        [
                            201.0,
                            412.0,
                            "L"
                        ],
                        [
                            200.0,
                            413.0,
                            "L"
                        ],
                        [
                            200.0,
                            415.0,
                            "L"
                        ],
                        [
                            199.0,
                            416.0,
                            "L"
                        ],
                        [
                            199.0,
                            419.0,
                            "L"
                        ],
                        [
                            198.0,
                            420.0,
                            "L"
                        ],
                        [
                            198.0,
                            422.0,
                            "L"
                        ],
                        [
                            197.0,
                            423.0,
                            "L"
                        ],
                        [
                            197.0,
                            424.0,
                            "L"
                        ],
                        [
                            195.0,
                            426.0,
                            "L"
                        ],
                        [
                            195.0,
                            427.0,
                            "L"
                        ],
                        [
                            193.0,
                            429.0,
                            "L"
                        ],
                        [
                            193.0,
                            430.0,
                            "L"
                        ],
                        [
                            191.0,
                            432.0,
                            "L"
                        ],
                        [
                            190.0,
                            432.0,
                            "L"
                        ],
                        [
                            188.0,
                            434.0,
                            "L"
                        ],
                        [
                            187.0,
                            434.0,
                            "L"
                        ],
                        [
                            186.0,
                            435.0,
                            "L"
                        ],
                        [
                            186.0,
                            436.0,
                            "L"
                        ],
                        [
                            185.0,
                            437.0,
                            "L"
                        ],
                        [
                            182.0,
                            437.0,
                            "L"
                        ],
                        [
                            181.0,
                            438.0,
                            "L"
                        ],
                        [
                            180.0,
                            438.0,
                            "L"
                        ],
                        [
                            179.0,
                            439.0,
                            "L"
                        ],
                        [
                            174.0,
                            439.0,
                            "L"
                        ],
                        [
                            173.0,
                            440.0,
                            "L"
                        ],
                        [
                            146.0,
                            440.0,
                            "L"
                        ],
                        [
                            145.0,
                            439.0,
                            "L"
                        ],
                        [
                            144.0,
                            439.0,
                            "L"
                        ],
                        [
                            143.0,
                            438.0,
                            "L"
                        ],
                        [
                            142.0,
                            438.0,
                            "L"
                        ],
                        [
                            141.0,
                            437.0,
                            "L"
                        ],
                        [
                            141.0,
                            436.0,
                            "L"
                        ],
                        [
                            139.0,
                            434.0,
                            "L"
                        ],
                        [
                            139.0,
                            433.0,
                            "L"
                        ],
                        [
                            138.0,
                            432.0,
                            "L"
                        ],
                        [
                            138.0,
                            431.0,
                            "L"
                        ],
                        [
                            136.0,
                            429.0,
                            "L"
                        ],
                        [
                            136.0,
                            428.0,
                            "L"
                        ],
                        [
                            135.0,
                            427.0,
                            "L"
                        ],
                        [
                            135.0,
                            426.0,
                            "L"
                        ],
                        [
                            134.0,
                            425.0,
                            "L"
                        ],
                        [
                            134.0,
                            424.0,
                            "L"
                        ],
                        [
                            133.0,
                            423.0,
                            "L"
                        ],
                        [
                            133.0,
                            422.0,
                            "L"
                        ],
                        [
                            132.0,
                            421.0,
                            "L"
                        ],
                        [
                            132.0,
                            419.0,
                            "L"
                        ],
                        [
                            131.0,
                            418.0,
                            "L"
                        ],
                        [
                            131.0,
                            415.0,
                            "L"
                        ],
                        [
                            130.0,
                            414.0,
                            "L"
                        ],
                        [
                            130.0,
                            411.0,
                            "L"
                        ],
                        [
                            129.0,
                            410.0,
                            "L"
                        ],
                        [
                            129.0,
                            405.0,
                            "L"
                        ],
                        [
                            128.0,
                            404.0,
                            "L"
                        ],
                        [
                            128.0,
                            396.0,
                            "L"
                        ],
                        [
                            126.0,
                            396.0,
                            "L"
                        ],
                        [
                            125.0,
                            395.0,
                            "L"
                        ],
                        [
                            122.0,
                            395.0,
                            "L"
                        ],
                        [
                            121.0,
                            394.0,
                            "L"
                        ],
                        [
                            119.0,
                            394.0,
                            "L"
                        ],
                        [
                            118.0,
                            393.0,
                            "L"
                        ],
                        [
                            116.0,
                            393.0,
                            "L"
                        ],
                        [
                            115.0,
                            392.0,
                            "L"
                        ],
                        [
                            113.0,
                            392.0,
                            "L"
                        ],
                        [
                            112.0,
                            391.0,
                            "L"
                        ],
                        [
                            109.0,
                            391.0,
                            "L"
                        ],
                        [
                            108.0,
                            390.0,
                            "L"
                        ],
                        [
                            106.0,
                            390.0,
                            "L"
                        ],
                        [
                            105.0,
                            389.0,
                            "L"
                        ],
                        [
                            103.0,
                            389.0,
                            "L"
                        ],
                        [
                            102.0,
                            388.0,
                            "L"
                        ],
                        [
                            99.0,
                            388.0,
                            "L"
                        ],
                        [
                            98.0,
                            387.0,
                            "L"
                        ],
                        [
                            96.0,
                            387.0,
                            "L"
                        ],
                        [
                            95.0,
                            386.0,
                            "L"
                        ],
                        [
                            93.0,
                            386.0,
                            "L"
                        ],
                        [
                            92.0,
                            385.0,
                            "L"
                        ],
                        [
                            90.0,
                            385.0,
                            "L"
                        ],
                        [
                            89.0,
                            384.0,
                            "L"
                        ],
                        [
                            86.0,
                            384.0,
                            "L"
                        ],
                        [
                            85.0,
                            383.0,
                            "L"
                        ],
                        [
                            83.0,
                            383.0,
                            "L"
                        ],
                        [
                            82.0,
                            382.0,
                            "L"
                        ],
                        [
                            80.0,
                            382.0,
                            "L"
                        ],
                        [
                            79.0,
                            381.0,
                            "L"
                        ],
                        [
                            78.0,
                            381.0,
                            "L"
                        ],
                        [
                            77.0,
                            382.0,
                            "L"
                        ],
                        [
                            73.0,
                            382.0,
                            "L"
                        ],
                        [
                            72.0,
                            383.0,
                            "L"
                        ],
                        [
                            71.0,
                            383.0,
                            "L"
                        ],
                        [
                            70.0,
                            384.0,
                            "L"
                        ],
                        [
                            55.0,
                            384.0,
                            "L"
                        ],
                        [
                            54.0,
                            383.0,
                            "L"
                        ],
                        [
                            54.0,
                            377.0,
                            "L"
                        ],
                        [
                            46.0,
                            377.0,
                            "L"
                        ],
                        [
                            45.0,
                            378.0,
                            "L"
                        ],
                        [
                            44.0,
                            378.0,
                            "L"
                        ],
                        [
                            43.0,
                            379.0,
                            "L"
                        ],
                        [
                            42.0,
                            379.0,
                            "L"
                        ],
                        [
                            41.0,
                            380.0,
                            "L"
                        ],
                        [
                            40.0,
                            380.0,
                            "L"
                        ],
                        [
                            39.0,
                            381.0,
                            "L"
                        ],
                        [
                            38.0,
                            381.0,
                            "L"
                        ],
                        [
                            37.0,
                            382.0,
                            "L"
                        ],
                        [
                            36.0,
                            382.0,
                            "L"
                        ],
                        [
                            35.0,
                            383.0,
                            "L"
                        ],
                        [
                            34.0,
                            383.0,
                            "L"
                        ],
                        [
                            33.0,
                            384.0,
                            "L"
                        ],
                        [
                            18.0,
                            384.0,
                            "L"
                        ],
                        [
                            17.0,
                            383.0,
                            "L"
                        ],
                        [
                            17.0,
                            382.0,
                            "L"
                        ],
                        [
                            15.0,
                            382.0,
                            "L"
                        ],
                        [
                            14.0,
                            381.0,
                            "L"
                        ],
                        [
                            13.0,
                            382.0,
                            "L"
                        ],
                        [
                            11.0,
                            382.0,
                            "L"
                        ],
                        [
                            10.0,
                            383.0,
                            "L"
                        ],
                        [
                            7.0,
                            383.0,
                            "L"
                        ],
                        [
                            6.0,
                            384.0,
                            "L"
                        ],
                        [
                            4.0,
                            384.0,
                            "L"
                        ],
                        [
                            3.0,
                            385.0,
                            "L"
                        ],
                        [
                            0.0,
                            385.0,
                            "L"
                        ],
                        [
                            0.0,
                            479.0,
                            "L"
                        ],
                        [
                            458.0,
                            479.0,
                            "L"
                        ],
                        [
                            458.0,
                            477.0,
                            "L"
                        ],
                        [
                            457.0,
                            476.0,
                            "L"
                        ],
                        [
                            457.0,
                            470.0,
                            "L"
                        ],
                        [
                            456.0,
                            469.0,
                            "L"
                        ],
                        [
                            456.0,
                            464.0,
                            "L"
                        ],
                        [
                            455.0,
                            463.0,
                            "L"
                        ],
                        [
                            455.0,
                            458.0,
                            "L"
                        ],
                        [
                            454.0,
                            457.0,
                            "L"
                        ],
                        [
                            454.0,
                            448.0,
                            "L"
                        ],
                        [
                            453.0,
                            447.0,
                            "L"
                        ],
                        [
                            453.0,
                            437.0,
                            "L"
                        ],
                        [
                            452.0,
                            436.0,
                            "L"
                        ],
                        [
                            452.0,
                            417.0,
                            "L"
                        ],
                        [
                            451.0,
                            416.0,
                            "L"
                        ],
                        [
                            451.0,
                            415.0,
                            "L"
                        ],
                        [
                            449.0,
                            413.0,
                            "L"
                        ],
                        [
                            449.0,
                            412.0,
                            "L"
                        ],
                        [
                            447.0,
                            410.0,
                            "L"
                        ],
                        [
                            447.0,
                            409.0,
                            "L"
                        ],
                        [
                            444.0,
                            406.0,
                            "L"
                        ],
                        [
                            444.0,
                            405.0,
                            "L"
                        ],
                        [
                            442.0,
                            403.0,
                            "L"
                        ],
                        [
                            442.0,
                            402.0,
                            "L"
                        ],
                        [
                            440.0,
                            400.0,
                            "L"
                        ],
                        [
                            440.0,
                            399.0,
                            "L"
                        ],
                        [
                            437.0,
                            396.0,
                            "L"
                        ],
                        [
                            437.0,
                            395.0,
                            "L"
                        ],
                        [
                            435.0,
                            393.0,
                            "L"
                        ],
                        [
                            435.0,
                            392.0,
                            "L"
                        ],
                        [
                            433.0,
                            390.0,
                            "L"
                        ],
                        [
                            433.0,
                            389.0,
                            "L"
                        ],
                        [
                            430.0,
                            386.0,
                            "L"
                        ],
                        [
                            430.0,
                            385.0,
                            "L"
                        ],
                        [
                            428.0,
                            383.0,
                            "L"
                        ],
                        [
                            428.0,
                            382.0,
                            "L"
                        ],
                        [
                            426.0,
                            380.0,
                            "L"
                        ],
                        [
                            426.0,
                            379.0,
                            "L"
                        ],
                        [
                            423.0,
                            376.0,
                            "L"
                        ],
                        [
                            423.0,
                            375.0,
                            "L"
                        ],
                        [
                            421.0,
                            373.0,
                            "L"
                        ],
                        [
                            421.0,
                            372.0,
                            "L"
                        ],
                        [
                            419.0,
                            370.0,
                            "L"
                        ],
                        [
                            419.0,
                            369.0,
                            "L"
                        ],
                        [
                            416.0,
                            366.0,
                            "L"
                        ],
                        [
                            416.0,
                            365.0,
                            "L"
                        ],
                        [
                            414.0,
                            363.0,
                            "L"
                        ],
                        [
                            414.0,
                            362.0,
                            "L"
                        ],
                        [
                            412.0,
                            360.0,
                            "L"
                        ],
                        [
                            412.0,
                            359.0,
                            "L"
                        ],
                        [
                            409.0,
                            356.0,
                            "L"
                        ],
                        [
                            409.0,
                            355.0,
                            "L"
                        ],
                        [
                            408.0,
                            354.0,
                            "L"
                        ],
                        [
                            400.0,
                            354.0,
                            "L"
                        ],
                        [
                            399.0,
                            353.0,
                            "L"
                        ],
                        [
                            398.0,
                            353.0,
                            "L"
                        ],
                        [
                            397.0,
                            352.0,
                            "L"
                        ],
                        [
                            396.0,
                            352.0,
                            "L"
                        ],
                        [
                            394.0,
                            350.0,
                            "L"
                        ],
                        [
                            393.0,
                            350.0,
                            "L"
                        ],
                        [
                            392.0,
                            349.0,
                            "L"
                        ],
                        [
                            391.0,
                            349.0,
                            "L"
                        ],
                        [
                            390.0,
                            348.0,
                            "L"
                        ],
                        [
                            389.0,
                            348.0,
                            "L"
                        ],
                        [
                            387.0,
                            346.0,
                            "L"
                        ],
                        [
                            385.0,
                            346.0,
                            "L"
                        ],
                        [
                            383.0,
                            344.0,
                            "L"
                        ],
                        [
                            383.0,
                            342.0,
                            "L"
                        ],
                        [
                            382.0,
                            341.0,
                            "L"
                        ],
                        [
                            382.0,
                            338.0,
                            "L"
                        ],
                        [
                            253.0,
                            338.0,
                            "L"
                        ]
                    ]
                }
            ]
        }
    ],
    "attributes": {
        "weather": "clear",
        "scene": "city street",
        "timeofday": "night"
    }
}