{
    "objects": [
        {
            "category": "obstacle",
            "id": 0,
            "attributes": {
                "occluded": false,
                "truncated": false,
                "trafficLightColor": "none"
            },
            "box2d": {
                "x1": 461.0,
                "y1": 229.0,
                "x2": 640.0,
                "y2": 480.0
            }
        },
        {
            "category": "obstacle",
            "id": 1,
            "attributes": {
                "occluded": false,
                "truncated": false,
                "trafficLightColor": "none"
            },
            "box2d": {
                "x1": 0.0,
                "y1": 0.0,
                "x2": 175.0,
                "y2": 480.0
            }
        }
    ]
}